{
    "type": "FeatureCollection",
    "name": "equip_mosquees_ci",
    "crs": {
        "type": "name",
        "properties": {
            "name": "urn:ogc:def:crs:OGC:1.3:CRS84"
        }
    },
    "features": [
        {
            "type": "Feature",
            "properties": {
                "UserID": null,
                "osm_id": null,
                "timestamp": null,
                "name": "Mosquée de N'Doucy",
                "type": "place_of_worship",
                "Type_1": null,
                "layer": null,
                "path": null,
                "type_cat": null
            },
            "geometry": {
                "type": "Point",
                "coordinates": [
                    -4.761075143065357,
                    5.863857712778747
                ]
            }
        }
    ]
}